fastui_admin/__about__.py
fastui_admin/__init__.py
fastui_admin-0.1.0.dist-info/METADATA
fastui_admin-0.1.0.dist-info/WHEEL
fastui_admin-0.1.0.dist-info/licenses/LICENSE
fastui_admin-0.1.0.dist-info/RECORD
